codecs2.py
codecs2-0.1.0.dist-info/LICENSE.txt
codecs2-0.1.0.dist-info/METADATA
codecs2-0.1.0.dist-info/WHEEL
codecs2-0.1.0.dist-info/top_level.txt
codecs2-0.1.0.dist-info/RECORD
