Metadata-Version: 2.1
Name: codecs2
Version: 0.1.0
Summary: A new interface for bytes/str codecs
Author-email: Karl Knechtel <zahlman@proton.me>
License: MIT License
Project-URL: bugs, https://github.com/zahlman/codecs2/issues
Project-URL: changelog, https://github.com/zahlman/codecs2/blob/master/changelog.md
Project-URL: homepage, https://github.com/zahlman/codecs2
Classifier: Development Status :: 1 - Planning
Classifier: Programming Language :: Python :: 3
License-File: LICENSE.txt
